Workbook

Sheet Thông tin vắn tắt về các thành 
A1: STT | B1: Họ và tên | C1: Năm sinh | D1: Đơn vị học tập/làm việc | E1: Chuyên ngành/ Lĩnh vực làm việc | F1: Vai trò trong dự án | G1: Ghi chú
A2: 1 | B2: Tống Ngọc Khang | C2: 2008 | D2: Đại học Kinh tế Thành phố Hồ Chí Minh - UEH | E2: Kiểm toán | F2: Trưởng nhóm, Quản lý Giải pháp & Chất lượng
A3: 2 | B3: Phạm Quốc Thanh | C3: 2005 | D3: Đại học Quốc tế - Đại học Quốc gia Thành phố Hồ Chí Minh | E3: Tài chính / AI Products | F3: Xây dựng Website, Trí tuệ nhân tạo (AI)
A4: 3 | B4: Nguyễn Ngọc Khánh Phương | C4: 2007 | D4: Trường Đại học Ngoại Thương - Phân hiệu TP.HCM | E4: Product Marketing | F4: Lên kế hoạch kinh doanh, ý tưởng kinh doanh
A5: 4 | B5: Nguyễn Hồng Phúc | C5: 2006 | D5: Trường đại học FPT Hà Nội | E5: Tài Chính | F5: Quản lý Dự án & Lập kế hoạch Tài chính
A6: 5 | B6: Nguyễn Quang Chiến | C6: 2007 | D6: Đại học Bách Khoa - Đại học Đà Nẵng | E6: AI Products | F6: Xây dựng Website, Trí tuệ nhân tạo (AI)

Sheet Business Model Canvas
A1: Business Model Canvas
A2: Đối tác chính (Key Partners) | B2: Hoạt động chính (Key Activities) | C2: Tuyên bố giá trị (Value Propositions) | D2: Quan hệ khách hàng (Customer Relationships) | E2: Phân khúc khách hàng (Customer Segments)
A4: Nguồn lực chính (Key Resources) | B4: Kênh truyền thông & phân phối (Channels) | C4: Cơ cấu chi phí (Cost Structure)

Sheet Tài Chính 
A1: Danh mục | B1: Chỉ tiêu chi tiết | C1: Nội dung cụ thể
A2: Nguồn thu | B2: Phí thuê bao (Subscription)
B3: Phí triển khai & tích hợp
B4: Tư vấn & báo cáo ESG | E4: Dự toán chi phí | J4: Chỉ tiêu | K4: Năm 0 (2026) | L4: Năm 1 (2027) | M4: Năm 2 (2028) | N4: Năm 3 (2029) | O4: Năm 4 (2030) | P4: Năm 5 (2031)
B5: Phí kết nối đơn chiều về | E5: STT | F5: Khoản mục chi phí | G5: Nội dung chi tiết | H5: Dự toán (VND) | J5: Doanh thu dự kiến
B6: Hoa hồng đối tác xanh | E6: 1 | F6: Phát triển sản phẩm/công nghệ | G6: Chi phí lập trình xây dựng nền tảng (web + app di động cho tài xế) Chi phí thiết kế UI/UX Chi phí xây dựng thuật toán tối ưu tuyến (VRP) ban đầu Chi phí tích hợp API bản đồ/GPS/giao thông lần đầu (setup fee nếu có) Chi phí xây dựng dashboard phân tích, báo cáo CO₂ Chi phí kiểm thử (QA/testing) trước khi ra mắt | J6: Chi phí vận hành
A7: Hiệu quả tài chính | E7: 2 | F7: Hạ tầng kỹ thuật | G7: Mua/thiết lập server (nếu không dùng cloud pay-as-you-go) Thiết lập cơ sở dữ liệu ban đầu Thiết lập hệ thống bảo mật, mã hóa dữ liệu | J7: Khấu hao
E8: 3 | F8: Pháp lý & hành chính | G8: Chi phí mở tài khoản ngân hàng doanh nghiệp Chi phí khởi tạo và cài đặt phần mềm hóa đơn điện tử Phí cung cấp thông tin doanh nghiệp Chi phí mua chữ ký số khai thuế Chi phí khắc con dấu và đăng cáo mẫu dấu Chi phí làm biển hiệu Phí sử dụng hóa đơn điện tử Chi phí soạn thảo hợp đồng với đối tác dữ liệu bản đồ/GPS Phí dịch vụ đăng ký logo độc quyền, bản quyền thương hiệu, nhãn hiệu Lệ phí nộp nhà nước đăng ký độc quyền thương hiệu Tư vấn pháp lý ban đầu | H8: =SUM(CAPEX!G15:G25) | J8: Lợi nhuận trước thuế
E9: 4 | F9: Thiết bị & tài sản cố định | G9: Laptop, thiết bị làm việc cho đội ngũ Thiết bị demo (nếu cần trình diễn cho khách hàng pilot)
E10: 5 | F10: Nghiên cứu & phát triển ban đầu | G10: Chi phí khảo sát thị trường, phỏng vấn doanh nghiệp (trước khi build) Chi phí thuê chuyên gia tư vấn thiết kế hệ thống (one-time) | J10: Hạng mục (VNĐ) | K10: 2026 (Năm 0) | L10: 2027 (Năm 1) | M10: 2028 (Năm 2) | N10: 2029 (Năm 3) | O10: 2030 (Năm 4) | P10: 2031 (Năm 5)
A11: CAPEX (đầu tư ban đầu - một lần) 1. Phát triển sản phẩm/công nghệ Chi phí lập trình xây dựng nền tảng (web + app di động cho tài xế) Chi phí thiết kế UI/UX Chi phí xây dựng thuật toán tối ưu tuyến (VRP) ban đầu Chi phí tích hợp API bản đồ/GPS/giao thông lần đầu (setup fee nếu có) Chi phí xây dựng dashboard phân tích, báo cáo CO₂ Chi phí kiểm thử (QA/testing) trước khi ra mắt 2. Hạ tầng kỹ thuật Mua/thiết lập server (nếu không dùng cloud pay-as-you-go) Thiết lập cơ sở dữ liệu ban đầu Thiết lập hệ thống bảo mật, mã hóa dữ liệu 3. Pháp lý & hành chính Chi phí mở tài khoản ngân hàng doanh nghiệp Chi phí khởi tạo và cài đặt phần mềm hóa đơn điện tử Phí cung cấp thông tin doanh nghiệp Chi phí mua chữ ký số khai thuế Chi phí khắc con dấu và đăng cáo mẫu dấu Chi phí làm biển hiệu Phí sử dụng hóa đơn điện tử Chi phí soạn thảo hợp đồng với đối tác dữ liệu bản đồ/GPS Phí dịch vụ đăng ký logo độc quyền, bản quyền thương hiệu, nhãn hiệu Lệ phí nộp nhà nước đăng ký độc quyền thương hiệu Tư vấn pháp lý ban đầu 4. Thiết bị & tài sản cố định Laptop, thiết bị làm việc cho đội ngũ Thiết bị demo (nếu cần trình diễn cho khách hàng pilot) 5. Nghiên cứu & phát triển ban đầu Chi phí khảo sát thị trường, phỏng vấn doanh nghiệp (trước khi build) Chi phí thuê chuyên gia tư vấn thiết kế hệ thống (one-time) OPEX (vận hành - định kỳ theo tháng/quý) 1. Chi phí công nghệ vận hành Phí API bản đồ (Google Maps/Mapbox/HERE...) theo lượt gọi Phí dữ liệu giao thông thời gian thực Phí hosting/cloud server (AWS, GCP, Azure...) Phí lưu trữ dữ liệu (storage) Phí duy trì bảo mật, SSL, backup định kỳ Phí bảo trì, sửa lỗi hệ thống 2. Nhân sự Lương đội kỹ thuật (dev, duy trì hệ thống) Lương đội kinh doanh/sales Lương đội chăm sóc khách hàng/hỗ trợ vận hành Lương/thù lao quản lý dự án Chi phí thuê chuyên gia tư vấn dài hạn (logistics, đo lường CO₂, VRP) nếu có Bảo hiểm xã hội, phúc lợi nhân viên (nếu tuyển chính thức) 3. Vận hành pilot/khách hàng Chi phí hỗ trợ kỹ thuật onsite/online cho DN thử nghiệm Chi phí đào tạo, hướng dẫn sử dụng cho DN và tài xế Chi phí thu thập, làm sạch, hiệu chỉnh dữ liệu thực tế Chi phí chương trình dùng thử miễn phí (coi là chi phí "customer acquisition") 4. Marketing & bán hàng Quảng cáo online (Facebook, LinkedIn, Google Ads) Chi phí tham gia hội thảo, triển lãm logistics/ESG Chi phí sản xuất nội dung truyền thông (video, bài viết, case study) Chi phí quà tặng/khuyến mãi cho khách hàng pilot 5. Chi phí văn phòng & hành chính Thuê văn phòng (nếu có), điện, nước, internet Công cụ làm việc: Google Workspace, Slack, Zoom, phần mềm quản lý dự án Văn phòng phẩm 6. Chi phí tài chính & pháp lý định kỳ Kế toán, kiểm toán Thuế Gia hạn giấy phép, hợp đồng đối tác dữ liệu (hàng năm) 7. Chi phí đo lường & báo cáo Công cụ/phần mềm đo lường CO₂ (nếu thuê ngoài thay vì tự xây) Chi phí lập báo cáo ESG định kỳ cho khách hàng 8. Dự phòng rủi ro Quỹ dự phòng phát sinh (thường 10-15% tổng OPEX) | E11: 6 | F11: Chi phí công nghệ vận hành | G11: Phí API bản đồ (Google Maps/Mapbox/HERE...) theo lượt gọi Phí dữ liệu giao thông thời gian thực Phí hosting/cloud server (AWS, GCP, Azure...) Phí lưu trữ dữ liệu (storage) Phí duy trì bảo mật, SSL, backup định kỳ Phí bảo trì, sửa lỗi hệ thống | J11: A. DÒNG TIỀN TỪ HĐKD
E12: 7 | F12: Nhân sự | G12: Lương đội kỹ thuật (dev, duy trì hệ thống) Lương đội kinh doanh/sales Lương đội chăm sóc khách hàng/hỗ trợ vận hành Lương/thù lao quản lý dự án Chi phí thuê chuyên gia tư vấn dài hạn (logistics, đo lường CO₂, VRP) nếu có Bảo hiểm xã hội, phúc lợi nhân viên (nếu tuyển chính thức) | J12: 1. Doanh thu dự kiến
E13: 8 | F13: Vận hành pilot/khách hàng | G13: Chi phí hỗ trợ kỹ thuật onsite/online cho DN thử nghiệm Chi phí đào tạo, hướng dẫn sử dụng cho DN và tài xế Chi phí thu thập, làm sạch, hiệu chỉnh dữ liệu thực tế Chi phí chương trình dùng thử miễn phí (coi là chi phí "customer acquisition") | J13: 2. Chi phí vận hành
E14: 9 | F14: Marketing & bán hàng | G14: Quảng cáo online (Facebook, LinkedIn, Google Ads) Chi phí tham gia hội thảo, triển lãm logistics/ESG Chi phí sản xuất nội dung truyền thông (video, bài viết, case study) Chi phí quà tặng/khuyến mãi cho khách hàng pilot | J14: 3. Thuế TNDN (20%)
E15: 10 | F15: Chi phí văn phòng & hành chính | G15: Thuê văn phòng (nếu có), điện, nước, internet Công cụ làm việc: Google Workspace, Slack, Zoom, phần mềm quản lý dự án Văn phòng phẩm | J15: Dòng thuần HĐKD (CFO)
E16: 11 | F16: Chi phí tài chính & pháp lý định kỳ | G16: Kế toán, kiểm toán Thuế Gia hạn giấy phép, hợp đồng đối tác dữ liệu (hàng năm) | J16: B. DÒNG TIỀN TỪ HĐĐT
E17: 12 | F17: Chi phí đo lường & báo cáo | G17: Công cụ/phần mềm đo lường CO₂ (nếu thuê ngoài thay vì tự xây) Chi phí lập báo cáo ESG định kỳ cho khách hàng | J17: 1. Vốn đầu tư ban đầu
E18: 13 | F18: Dự phòng rủi ro | G18: Quỹ dự phòng phát sinh (thường 10-15% tổng OPEX) | J18: Dòng thuần HĐĐT (CFI)
J19: C. TỔNG DÒNG TIỀN THUẦN
J21: Chi phí vốn ước tính
J22: Thời gian hoàn vốn
J23: Thời gian hoàn vốn có chiết khấu
J24: NPV - Giá trị hiện tại ròng
J25: IRR - Tỷ suất hoàn vốn nội bộ

Sheet CAPEX
A1: CAPEX
A2: Name of Capitals | D2: Units | E2: Quantity | F2: Price (VND) | G2: Total (VND) | H2: Note
A3: 1. Phát triển sản phẩm/công nghệ
A4: Chi phí lập trình xây dựng nền tảng (web + app di động cho tài xế) | D4: Gói MVP | E4: 1 | F4: 45000000 | G4: =E4*F4 | H4: Xây dựng Web Điều phối + App di động Flutter cho tài xế (3-4 tháng MVP, 2 dev core)
A5: Chi phí thiết kế UI/UX | D5: Gói thiết kế | E5: 1 | F5: 10000000 | G5: =E5*F5 | H5: Hệ thống Figma: Web Portal Điều phối, App Tài xế, Dashboard Báo cáo CO2
A6: Chi phí xây dựng thuật toán tối ưu tuyến (VRP) ban đầu | D6: Module Core | E6: 1 | F6: 20000000 | G6: =E6*F6 | H6: Giải thuật VRPTW đa điểm kết hợp ràng buộc tải trọng xe, khung giờ giao & tình trạng giao thông
A7: Chi phí tích hợp API bản đồ/GPS/giao thông lần đầu (setup fee nếu có) | D7: Lần tích hợp | E7: 1 | F7: 4000000 | G7: =E7*F7 | H7: Setup fee, SDK integration, Webhook kết nối dữ liệu GPS và API bản đồ Goong/Mapbox
A8: Chi phí xây dựng dashboard phân tích, báo cáo CO₂ | D8: Module Dashboard | E8: 1 | F8: 12000000 | G8: =E8*F8 | H8: Dashboard phân tích phát thải chuẩn GLEC Framework v3.0 / ISO 14083:2023 / GHG Protocol
A9: Chi phí kiểm thử (QA/testing) trước khi ra mắt | D9: Gói QA/QC | E9: 1 | F9: 6000000 | G9: =E9*F9 | H9: Manual QA test kịch bản bưu cục + Automated Load Testing 500 CCU tài xế
A10: 2. Hạ tầng kỹ thuật
A11: Mua/thiết lập server (nếu không dùng cloud pay-as-you-go) | D11: Gói setup | E11: 1 | F11: 3500000 | G11: =E11*F11 | H11: Khởi tạo cụm Docker/K8s, VPC mạng riêng an toàn, CI/CD GitHub Actions deploy
A12: Thiết lập cơ sở dữ liệu ban đầu | D12: Gói CSDL | E12: 1 | F12: 2500000 | G12: =E12*F12 | H12: PostgreSQL + PostGIS (GIS spatial routing engine) + Redis Caching
A13: Thiết lập hệ thống bảo mật, mã hóa dữ liệu | D13: Gói bảo mật | E13: 1 | F13: 4000000 | G13: =E13*F13 | H13: Tuân thủ NĐ 13/2023/NĐ-CP bảo vệ dữ liệu cá nhân, SSL EV Wildcard, Cloudflare WAF
A14: 3. Pháp lý & hành chính
A15: Chi phí mở tài khoản ngân hàng doanh nghiệp | D15: Tài khoản | E15: 1 | F15: 0 | G15: =E15*F15
A16: Chi phí khởi tạo và cài đặt phần mềm hóa đơn điện tử | D16: Lần | E16: 1 | F16: 1000000 | G16: =E16*F16 | H16: Phí khởi tạo phần mềm hóa đơn điện tử MISA meInvoice (chuẩn niêm yết 2026)
A17: Phí cung cấp thông tin doanh nghiệp | D17: Lần | E17: 1 | F17: 2000000 | G17: =E17*F17 | H17: Dịch vụ ĐKKD thành lập DN trọn gói + Lệ phí nhà nước + Bố cáo điện tử Cổng thông tin QG
A18: Chi phí mua chữ ký số khai thuế | D18: Gói | E18: 1 | F18: 1990000 | G18: =E18*F18 | H18: Chữ ký số Vina-CA / Viettel-CA (Gói 36 tháng bao gồm USB Token chuẩn giá đại lý 2026)
A19: Chi phí khắc con dấu và đăng cáo mẫu dấu | D19: Bộ | E19: 1 | F19: 450000 | G19: =E19*F19
A20: Chi phí làm biển hiệu | D20: Cái | E20: 1 | F20: 800000 | G20: =E20*F20
A21: Phí sử dụng hóa đơn điện tử | D21: Hóa đơn | E21: 1000 | F21: 1050 | G21: =E21*F21 | H21: 1,000 số hóa đơn điện tử MISA meInvoice (giá niêm yết 1.050.000 VNĐ)
A22: Chi phí soạn thảo hợp đồng với đối tác dữ liệu bản đồ/GPS | D22: Lần | E22: 1 | F22: 4000000 | G22: =E22*F22 | J22: =SUM(G15:G25) | K22: https://amis.misa.vn/136043/chi-phi-khi-thanh-lap-doanh-nghiep/ https://luatvietan.vn/chi-phi-thanh-lap-cong-ty.html https://ketoananpha.vn/dich-vu-dang-ky-thuong-hieu.html https://luatsudfc.vn/phi-dich-vu-tu-van-soan-thao-hop-dong.html? https://chukysotot.com/bang-gia-chu-ky-so-cap-nhat-moi-nhat/
A23: Phí dịch vụ đăng ký logo độc quyền, bản quyền thương hiệu, nhãn hiệu | D23: Lần | E23: 1 | F23: 1000000 | G23: =E23*F23
A24: Lệ phí nộp nhà nước đăng ký độc quyền thương hiệu | D24: Hồ sơ | E24: 1 | F24: 1120000 | G24: =E24*F24 | H24: Lệ phí nhà nước theo TT 263/2016/TT-BTC & TT 63/2023/TT-BTC tại Cục SHTT (1 nhóm 6 SP/DV)
A25: Tư vấn pháp lý ban đầu | D25: Lần | E25: 1 | F25: 1990000 | G25: =E25*F25
A26: 4. Thiết bị & tài sản cố định
A27: Laptop, thiết bị làm việc cho đội ngũ | D27: Bộ thiết bị | E27: 2 | F27: 12500000 | G27: =E27*F27 | H27: 2 Laptop chuyên dụng dev/test phục vụ build môi trường và phân tích dữ liệu
A28: Thiết bị demo (nếu cần trình diễn cho khách hàng pilot) | D28: Chiếc | E28: 2 | F28: 3500000 | G28: =E28*F28 | H28: 2 Smartphone/Tablet cấu hình chuẩn test app tài xế onsite tại bưu cục pilot
A29: 5. Nghiên cứu & phát triển ban đầu
A30: Chi phí khảo sát thị trường, phỏng vấn doanh nghiệp (trước khi build) | D30: Đợt khảo sát | E30: 1 | F30: 5000000 | G30: =E30*F30 | H30: Chi phí đi lại, khảo sát thực tế và phỏng vấn 15-20 chủ bưu cục/quản lý vận tải TP.HCM
A31: Chi phí thuê chuyên gia tư vấn thiết kế hệ thống (one-time) | D31: Hợp đồng tư vấn | E31: 1 | F31: 10000000 | G31: =E31*F31 | H31: Tư vấn từ chuyên gia Logistics VLA và chuyên gia giải thuật VRP
A36: TỔNG CỘNG VỐN ĐẦU TƯ BAN ĐẦU (CAPEX) | G36: =SUM(G4:G9)+SUM(G11:G13)+SUM(G15:G25)+SUM(G27:G28)+SUM(G30:G31) | H36: Tổng vốn đầu tư ban đầu (được tham chiếu tự động sang bảng CASH FLOW)

Sheet Tài Chính 2
A1: A. Nguồn thu dự kiến
B2: Nguồn thu | C2: Mô tả | D2: Đối tượng thu | E2: Giai đoạn áp dụng | F2: Ưu tiên | H2: Giai đoạn pilot (4-6 tuần): không thu phí- đổi lại nhận dữ liệu vận hành thực tế để hiệu chỉnh thuật toán và làm căn cứ định giá. (này consider nên thu hay không nha)
A3: 1 | B3: Phí thuê bao (Subscription) | C3: Thu theo tháng, tính trên số phương tiện quản lý/số tuyến tối ưu; phân theo quy mô DN | D3: Toàn bộ khách hàng | E3: Sau pilot (GĐ 2-3) | F3: Cốt lõi của ngành
A4: 2 | B4: Phí triển khai & tích hợp | C4: Thu một lần: nhập dữ liệu, đào tạo, tích hợp phần mềm sẵn có | D4: Khách hàng mới | E4: Sau pilot (GĐ 2-3) | F4: Cốt lõi cho ứng dụng
A5: 3 | B5: Tư vấn & báo cáo ESG | C5: Tư vấn tối ưu chuyên sâu, báo cáo CO₂ chuẩn hóa cho DN xuất khẩu | D5: DN có nhu cầu ESG | E5: Mở rộng (GĐ 4-5) | F5: Bổ sung tùy theo doanh nghiệp cần hay không
A6: 4 | B6: Phí kết nối đơn chiều về | C6: Hoa hồng khi ghép đơn chiều về giữa các DN | D6: Mạng lưới logistics tuần hoàn | E6: GĐ 6 (dài hạn) | F6: Có thể phát triển thêm (nếu các đvvc họ đồng ý từ đầu)
A7: 5 | B7: Hoa hồng đối tác xanh | C7: Giới thiệu khách hàng cho đối tác xe điện/trạm sạc | D7: Đối tác sinh thái | E7: Mở rộng hệ sinh thái (dài hạn) | F7: Tiềm năng cho đvvc có xe điện
A9: B. Cơ cấu chi phí dự kiến | E9: C. Nhu cầu vốn theo giai đoạn
A10: Nhóm chi phí | B10: Nội dung | C10: Giai đoạn phát sinh | E10: Giai đoạn | F10: Nhu cầu vốn chính | G10: Mục đích sử dụng
A11: Công nghệ & dữ liệu | B11: Phí API bản đồ/GPS, dữ liệu giao thông; hạ tầng máy chủ, cơ sở dữ liệu, bảo mật | C11: Ngay từ MVP/pilot | E11: GĐ 1 - MVP | F11: Vốn nhỏ / nội bộ | G11: Hoàn thiện sản phẩm, kiểm chứng nhu cầu
A12: Phát triển sản phẩm | B12: Nhân sự lập trình, kiểm thử, hoàn thiện thuật toán VRP | C12: Xuyên suốt các giai đoạn | E12: GĐ 2 - Pilot TP.HCM | F12: Vốn hạt giống (seed) | G12: Phí API dữ liệu, vận hành thử nghiệm, hỗ trợ 3-5 DN pilot
A13: Vận hành pilot | B13: Hỗ trợ kỹ thuật cho DN thử nghiệm, khảo sát, thu thập dữ liệu | C13: Giai đoạn pilot | E13: GĐ 3 - Tối ưu công nghệ | F13: Vốn mở rộng (early-stage) | G13: Tuyển chuyên gia VRP/dữ liệu, nâng cấp hạ tầng
A14: Nhân sự chuyên môn bổ sung | B14: Chuyên gia VRP, phân tích dữ liệu, đo lường phát thải (theo mục V.2 đã nêu) | C14: Từ giai đoạn tối ưu công nghệ | E14: GĐ 4-5 - Mở rộng địa bàn & hệ sinh thái | F14: Vốn tăng trưởng | G14: Marketing, mở rộng đội ngũ, tích hợp đối tác
A15: Marketing & tiếp cận khách hàng | B15: Hội thảo, truyền thông, hợp tác hiệp hội/đối tác | C15: Từ giai đoạn pilot trở đi | E15: GĐ 6-7 - Logistics tuần hoàn & liên tỉnh | F15: Vốn quy mô lớn / gọi vốn vòng sau | G15: Xây dựng mạng lưới liên doanh nghiệp, mở rộng vùng địa lý
A16: Vận hành & duy trì hệ thống | B16: Chi phí server, hỗ trợ khách hàng, cập nhật bảo trì | C16: Khi thương mại hóa

Sheet Revenue forecasts
A1: Revenue 2027
A2: Tháng | C2: Sản lượng | D2: Doanh thu | F2: Sản lượng | G2: Doanh thu | I2: Sản lượng | J2: Doanh thu | L2: Sản lượng | M2: Doanh thu | O2: Sản lượng | P2: Doanh thu | Q2: Tổng doanh thu tháng (VNĐ)
A3: 1
A4: 2
A5: 3
A6: 4
A7: 5
A8: 6
A9: 7
A10: 8
A11: 9
A12: 10
A13: 11
A14: 12
A15: TỔNG DOANH THU NĂM 2027 | Q15: =SUM(Q3:Q14)

Sheet DEPRECIATION 
A1: DEPRECIATION
A2: No | B2: Hạng mục khấu hao | C2: Giá trị đầu tư (VND) | D2: Thời gian (năm) | E2: Khấu hao năm | F2: Khấu hao tháng

Sheet OPEX
A1: OPEX - 2027
A2: No. | B2: Name of Capitals | C2: Units | D2: Quantity | E2: Price (VND) | F2: Total/Tháng (VND) | G2: Total/Năm 2027 (VND) | H2: Note
A3: 1 | B3: 1. Chi phí công nghệ vận hành
A4: 1.1 | B4: Phí API bản đồ (Google Maps/Mapbox/HERE...) theo lượt gọi | C4: Tháng | D4: 1 | E4: 5000000 | F4: =D4*E4 | G4: =F4*12 | H4: DAU TB 57-171 (User_acquisition_plan), ~100k-150k routing calls/tháng
A5: 1.2 | B5: Phí dữ liệu giao thông thời gian thực | C5: Tháng | D5: 1 | E5: 2500000 | F5: =D5*E5 | G5: =F5*12 | H5: API dữ liệu giao thông thời gian thực (Traffic layer & congestion)
A6: 1.3 | B6: Phí hosting/cloud server (AWS, GCP, Azure...) | C6: Tháng | D6: 1 | E6: 3500000 | F6: =D6*E6 | G6: =F6*12 | H6: 2 Cụm máy chủ ứng dụng (Web Dispatch + Driver API Backend + Load Balancer)
A7: 1.4 | B7: Phí lưu trữ dữ liệu (storage) | C7: Tháng | D7: 1 | E7: 1200000 | F7: =D7*E7 | G7: =F7*12 | H7: Managed PostgreSQL/PostGIS Database + S3 Object Storage lưu trữ lịch sử chuyến
A8: 1.5 | B8: Phí duy trì bảo mật, SSL, backup định kỳ | C8: Tháng | D8: 1 | E8: 800000 | F8: =D8*E8 | G8: =F8*12 | H8: Chứng chỉ SSL định kỳ, sao lưu CSDL tự động hàng ngày, Cloudflare Security Pro
A9: 1.6 | B9: Phí bảo trì, sửa lỗi hệ thống | C9: Tháng | D9: 1 | E9: 1000000 | F9: =D9*E9 | G9: =F9*12 | H9: Giám sát lỗi tự động (Sentry), APM performance monitoring, bảo trì định kỳ
A10: 2 | B10: 2. Nhân sự
A11: 2.1 | B11: Lương đội kỹ thuật (dev, duy trì hệ thống) | C11: Tháng (2 người) | D11: 2 | E11: 12500000 | F11: =D11*E11 | G11: =F11*12 | H11: 2 Lập trình viên Fullstack/Mobile kiêm vận hành hệ thống (25,000,000 VND/tháng)
A12: 2.2 | B12: Lương đội kinh doanh/sales | C12: Tháng (1 người) | D12: 1 | E12: 10000000 | F12: =D12*E12 | G12: =F12*12 | H12: 1 Nhân viên Sales B2B tiếp cận các đơn vị vận chuyển và bưu cục logistics
A13: 2.3 | B13: Lương đội chăm sóc khách hàng/hỗ trợ vận hành | C13: Tháng (1 người) | D13: 1 | E13: 8000000 | F13: =D13*E13 | G13: =F13*12 | H13: 1 Nhân viên Onboarding, hướng dẫn và hỗ trợ kỹ thuật trực tiếp cho bưu cục và tài xế
A14: 2.4 | B14: Lương/thù lao quản lý dự án | C14: Tháng (1 người) | D14: 1 | E14: 12000000 | F14: =D14*E14 | G14: =F14*12 | H14: Thù lao Quản lý dự án (Project Manager / Product Owner) điều phối chung
A15: 2.5 | B15: Chi phí thuê chuyên gia tư vấn dài hạn (logistics, đo lường CO₂, VRP) nếu có | C15: Tháng | D15: 1 | E15: 4000000 | F15: =D15*E15 | G15: =F15*12 | H15: Thù lao cố vấn chuyên môn giải thuật VRP và phương pháp kiểm kê phát thải CO₂
A16: 2.6 | B16: Bảo hiểm xã hội, phúc lợi nhân viên (nếu tuyển chính thức) | C16: Tháng | D16: 1 | E16: 6450000 | F16: =D16*E16 | G16: =F16*12 | H16: Đóng BHXH, BHYT, BHTN theo Luật BHXH 2024 (Doanh nghiệp đóng 21.5% quỹ lương cơ bản)
A17: 3 | B17: 3. Vận hành pilot/khách hàng
A18: 3.1 | B18: Chi phí hỗ trợ kỹ thuật onsite/online cho DN thử nghiệm | C18: Tháng | D18: 1 | E18: 2500000 | F18: =D18*E18 | G18: =F18*12 | H18: Xăng xe, phụ cấp công tác trực tiếp tại các bưu cục thử nghiệm (2-4 bưu cục)
A19: 3.2 | B19: Chi phí đào tạo, hướng dẫn sử dụng cho DN và tài xế | C19: Tháng | D19: 1 | E19: 1500000 | F19: =D19*E19 | G19: =F19*12 | H19: In ấn tài liệu hướng dẫn nhanh, tổ chức các buổi đào tạo thực địa cho tài xế
A20: 3.3 | B20: Chi phí thu thập, làm sạch, hiệu chỉnh dữ liệu thực tế | C20: Tháng | D20: 1 | E20: 2000000 | F20: =D20*E20 | G20: =F20*12 | H20: Xử lý chuẩn hóa địa chỉ đơn hàng và hiệu chỉnh thông số tiêu hao nhiên liệu xe
A21: 3.4 | B21: Chi phí chương trình dùng thử miễn phí (coi là chi phí "customer acquisition") | C21: Tháng | D21: 1 | E21: 3000000 | F21: =D21*E21 | G21: =F21*12 | H21: Chi phí hỗ trợ/trợ giá dùng thử trong 4-6 tuần đầu để thu thập dữ liệu pilot
A22: 4 | B22: 4. Marketing & bán hàng
A23: 4.1 | B23: Quảng cáo online (Facebook, LinkedIn, Google Ads) | C23: Tháng | D23: 1 | E23: 4000000 | F23: =D23*E23 | G23: =F23*12 | H23: Chạy chiến dịch digital marketing nhắm vào nhóm quản lý chuỗi cung ứng/logistics
A24: 4.2 | B24: Chi phí tham gia hội thảo, triển lãm logistics/ESG | C24: Tháng (phân bổ) | D24: 1 | E24: 2500000 | F24: =D24*E24 | G24: =F24*12 | H24: Phân bổ chi phí tham dự các diễn đàn logistics xanh, triển lãm VLA, Green Expo
A25: 4.3 | B25: Chi phí sản xuất nội dung truyền thông (video, bài viết, case study) | C25: Tháng | D25: 1 | E25: 2500000 | F25: =D25*E25 | G25: =F25*12 | H25: Sản xuất video giới thiệu tính năng, bài viết case study chứng minh hiệu quả tiết kiệm
A26: 4.4 | B26: Chi phí quà tặng/khuyến mãi cho khách hàng pilot | C26: Tháng | D26: 1 | E26: 1200000 | F26: =D26*E26 | G26: =F26*12 | H26: Quà lưu niệm, tài trợ vật phẩm cho các bưu cục và tài xế tham gia pilot
A27: 5 | B27: 5. Chi phí văn phòng & hành chính
A28: 5.1 | B28: Thuê văn phòng (nếu có), điện, nước, internet | C28: Tháng | D28: 1 | E28: 6000000 | F28: =D28*E28 | G28: =F28*12 | H28: Thuê không gian làm việc Co-working Space / Vườn ươm khởi nghiệp
A29: 5.2 | B29: Công cụ làm việc: Google Workspace, Slack, Zoom, phần mềm quản lý dự án | C29: Tháng | D29: 1 | E29: 1500000 | F29: =D29*E29 | G29: =F29*12 | H29: Bản quyền Google Workspace Business, Slack Pro, Notion, Jira cho 5-8 tài khoản
A30: 5.3 | B30: Văn phòng phẩm | C30: Tháng | D30: 1 | E30: 600000 | F30: =D30*E30 | G30: =F30*12 | H30: Giấy in, bút, vật dụng văn phòng thiết yếu
A31: 6 | B31: 6. Chi phí tài chính & pháp lý định kỳ
A32: 6.1 | B32: Kế toán, kiểm toán | C32: Tháng | D32: 1 | E32: 1800000 | F32: =D32*E32 | G32: =F32*12 | H32: Thuê dịch vụ kế toán thuế và lập báo cáo tài chính trọn gói cho doanh nghiệp SME
A33: 6.2 | B33: Thuế | C33: Tháng (phân bổ) | D33: 1 | E33: 167000 | F33: =D33*E33 | G33: =F33*12 | H33: Lệ phí môn bài bậc 2 triệu/năm (miễn năm đầu 2026 theo NĐ 22/2020, đóng từ 2027)
A34: 6.3 | B34: Gia hạn giấy phép, hợp đồng đối tác dữ liệu (hàng năm) | C34: Tháng (phân bổ) | D34: 1 | E34: 800000 | F34: =D34*E34 | G34: =F34*12 | H34: Phân bổ phí gia hạn bản quyền dữ liệu và giấy phép liên quan
A35: 7 | B35: 7. Chi phí đo lường & báo cáo
A36: 7.1 | B36: Công cụ/phần mềm đo lường CO₂ (nếu thuê ngoài thay vì tự xây) | C36: Tháng | D36: 1 | E36: 1500000 | F36: =D36*E36 | G36: =F36*12 | H36: Cập nhật hệ số phát thải (Emission Factors) chuẩn quốc tế GLEC/IPCC từ cơ sở dữ liệu
A37: 7.2 | B37: Chi phí lập báo cáo ESG định kỳ cho khách hàng | C37: Tháng | D37: 1 | E37: 2000000 | F37: =D37*E37 | G37: =F37*12 | H37: Xuất báo cáo định lượng CO₂ tiết giảm và chứng nhận phát thải xanh cho khách hàng B2B
A38: 8 | B38: 8. Dự phòng rủi ro
A39: 8.1 | B39: Quỹ dự phòng phát sinh (10% tổng OPEX) | C39: Tháng | D39: 1 | E39: 11301700 | F39: =D39*E39 | G39: =F39*12 | H39: Trích lập 10% trên tổng chi phí vận hành hàng tháng để dự phòng biến động thị trường & chi phí đột xuất
A40: TOTAL | B40: TỔNG CỘNG OPEX VẬN HÀNH (ĐÃ BAO GỒM 10% DỰ PHÒNG) | F40: =SUM(F4:F9)+SUM(F11:F16)+SUM(F18:F21)+SUM(F23:F26)+SUM(F28:F30)+SUM(F32:F34)+SUM(F36:F37)+F39 | G40: =F40*12 | H40: TỔNG CỘNG CHI PHÍ VẬN HÀNH OPEX

Sheet FIXED COST
A1: Fixed Cost
F2: 2026 | G2: 2027 | H2: 2028 | I2: 2029 | J2: 2030 | K2: 2031 | L2: Chú thích
A3: No. | B3: Name of Capitals | C3: Units | D3: Quantity | E3: Price (VND) | F3: Total (VND) | G3: Total (VND) | H3: Total (VND) | I3: Total (VND) | J3: Total (VND) | K3: Total (VND)

Sheet VARIABLE COST
A1: Variable Cost
A2: 2026
A3: No. 1 | B3: Hạng mục chi phí | C3: Đơn vị | D3: Tháng 1 | E3: Tháng 2 | F3: Tháng 3 | G3: Tháng 4 | H3: Tháng 5 | I3: Tháng 6 | J3: Tháng 7 | K3: Tháng 8 | L3: Tháng 9 | M3: Tháng 10 | N3: Tháng 11 | O3: Tháng 12 | P3: Tổng

Sheet INCOME STATEMENT
A1: Income Statement | I1: Income Statement 2027
A2: No, | B2: Chỉ tiêu | C2: Năm 2027 (VND) | D2: Năm 2028 (VND) | E2: Năm 2029 (VND) | F2: Năm 2030 (VND) | G2: Năm 2031 (VND) | I2: Tháng | J2: Doanh thu (VND) | K2: COGS (VND) | L2: OPEX (VND) | M2: Khấu hao/tháng (VND) | N2: EBIT (VND) | O2: Thuế (20%) | P2: Lợi nhuận ròng (VND)
A3: 1 | B3: Doanh thu thuần (Net Revenue)
A4: 2 | B4: Giá vốn hàng bán (COGS)
A5: 3 | B5: Lợi nhuận gộp (Gross Profit)
A6: 4 | B6: Chi phí vận hành (OPEX)
A7: 5 | B7: Chi phí khấu hao
A8: 6 | B8: Lợi nhuận hoạt động (Operating Profit / EBIT)
A9: 7 | B9: Thu nhập khác (Other Income)
A10: 8 | B10: Chi phí khác (Other Expenses)
A11: 9 | B11: Lợi nhuận trước thuế (EBT)
A12: 10 | B12: Thuế thu nhập doanh nghiệp (CIT 20%)
A13: 11 | B13: Lợi nhuận ròng (Net Income After Tax)
A15: Tỷ suất lợi nhuận chính
A16: No, | B16: Chỉ số | C16: Năm 2026 | D16: Năm 2027 | E16: Năm 2028 | F16: Năm 2029 (VND) | G16: Năm 2030 (VND)
A17: 1 | B17: Gross Profit Margin (Biên lợi nhuận gộp) | C17: =(C3-C4)/C3 | D17: =(D3-D4)/D3 | E17: =(E3-E4)/E3 | F17: =(F3-F4)/F3 | G17: =(G3-G4)/G3
A18: 2 | B18: Operating Profit Margin (Biên lợi nhuận hoạt động) | C18: =C8/C3 | D18: =D8/D3 | E18: =E8/E3 | F18: =F8/F3 | G18: =G8/G3
A19: 3 | B19: Net Profit Margin (Biên lợi nhuận ròng) | C19: =C13/C3 | D19: =D13/D3 | E19: =E13/E3 | F19: =F13/F3 | G19: =G13/G3
A20: 4 | B20: COGS Ratio (Tỷ trọng giá vốn/doanh thu) | C20: =C4/C3 | D20: =D4/D3 | E20: =E4/E3 | F20: =F4/F3 | G20: =G4/G3
A21: 5 | B21: OPEX Ratio (Tỷ trọng chi phí vận hành/doanh thu) | C21: =C6/C3 | D21: =D6/D3 | E21: =E6/E3 | F21: =F6/F3 | G21: =G6/G3

Sheet CASH FLOW
A1: Financial indicators
A2: Year | B2: Cash flow | C2: Cumulative | D2: PV | E2: PV cumiulative
A3: 2026 | B3: =G23+G27 | C3: =B3 | D3: =B3 | E3: =D3
A4: 2027 | B4: =H23 | C4: =B4+C3 | D4: =(B4/1.15^1) | E4: =E3+D4
A5: 2028 | B5: =I23 | C5: =B5+C4 | D5: =(B5/1.15^2) | E5: =E4+D5
A6: 2029 | B6: =J23 | C6: =B6+C5 | D6: =(B6/1.15^3) | E6: =E5+D6
A7: 2030 | B7: =K23 | C7: =B7+C6 | D7: =(B7/1.15^4) | E7: =E6+D7
A8: 2031 | B8: =L23 | C8: =B8+C7 | D8: =(B8/1.15^5) | E8: =E7+D8
A9: Estimated Cost of capital
A10: Break even point | E10: =I7
A11: Payback Period/ Year | E11: =3+ ABS(C6)/B7
A12: Discounted Paypack period/ Year | E12: =3+ ABS(E6)/D7
A13: NPV | E13: {=NPV(E9,B4:B8)+B3}
A14: IRR | E14: =IRR(B3:B8)
F16: CASH FLOW
F17: Hạng mục | G17: Năm 0 (2026) | H17: Năm 1 (2027) | I17: Năm 2 (2028) | J17: Năm 3 (2029) | K17: Năm 4 (2030) | L17: Năm 5 (2031)
F18: A. DÒNG TIỀN TỪ HOẠT ĐỘNG KINH DOANH (Operating Activities)
F19: 1. Tiền nhận được từ sale | G19: 0 | H19: ='INCOME STATEMENT'!C3 | I19: ='INCOME STATEMENT'!D3 | J19: ='INCOME STATEMENT'!E3 | K19: ='INCOME STATEMENT'!F3 | L19: ='INCOME STATEMENT'!G3
F20: 2. Giá vốn bán hàng | G20: 0 | H20: ='INCOME STATEMENT'!C4 | I20: ='INCOME STATEMENT'!D4 | J20: ='INCOME STATEMENT'!E4 | K20: ='INCOME STATEMENT'!F4 | L20: ='INCOME STATEMENT'!G4
F21: 3. Chi phí vận hành OPEX | G21: 0 | H21: =OPEX!G40 | I21: ='INCOME STATEMENT'!D6 | J21: ='INCOME STATEMENT'!E6 | K21: ='INCOME STATEMENT'!F6 | L21: ='INCOME STATEMENT'!G6
F22: 4. Thuế TNDN phải nộp | G22: 0 | H22: 0 | I22: ='INCOME STATEMENT'!O31 | J22: ='INCOME STATEMENT'!E12 | K22: ='INCOME STATEMENT'!F12 | L22: ='INCOME STATEMENT'!G12
F23: Dòng tiền thuần từ HĐKD (CFO) | G23: =SUM(G19:G22) | H23: =H19-H20-H21-H22 | I23: ='INCOME STATEMENT'!N31-'INCOME STATEMENT'!O31+'INCOME STATEMENT'!M31 | J23: ='INCOME STATEMENT'!N47-'INCOME STATEMENT'!O47+'INCOME STATEMENT'!M47 | K23: ='INCOME STATEMENT'!N63-'INCOME STATEMENT'!O63+'INCOME STATEMENT'!M63 | L23: ='INCOME STATEMENT'!N79-'INCOME STATEMENT'!O79+'INCOME STATEMENT'!M79
F24: B. DÒNG TIỀN TỪ HOẠT ĐỘNG ĐẦU TƯ (Investing Activities)
F25: 1. Chi đầu tư tài sản cố định | G25: =-CAPEX!G36 | H25: 0 | I25: 0 | J25: 0 | K25: 0 | L25: 0
F26: 2. Thanh lý / Thu hồi TSCĐ | G26: 0 | H26: 0 | I26: 0 | J26: 0 | K26: 0 | L26: 0
F27: Dòng tiền thuần từ HĐĐT (CFI) | G27: =G25
F28: C. DÒNG TIỀN TỪ HOẠT ĐỘNG TÀI CHÍNH (Financing Activities)
F30: 1. Vốn góp / Huy động (Equity funding) | G30: ='Working capital requirement'!A3+CAPEX!G36 | H30: 0 | I30: 0 | J30: 0 | K30: 0 | L30: 0
F31: 2. Chi trả cổ tức / lãi vay | G31: 0 | H31: 0 | I31: 0 | J31: 0 | K31: 0 | L31: 0
F32: Dòng tiền thuần từ HĐTC (CFF) | G32: =SUM(G30:G31) | H32: 0 | I32: 0 | J32: 0 | K32: 0 | L32: 0
F34: D. TỔNG DÒNG TIỀN THUẦN (A + B + C) | G34: =G27+G23+G32 | H34: =H23+H27+H32 | I34: =I23+I27+I32 | J34: =J23+J27+J32 | K34: =K23+K27+K32 | L34: =L23+L27+L32
F35: Tiền tồn đầu kỳ | G35: 0 | H35: =G36 | I35: =H36 | J35: =I36 | K35: =J36 | L35: =K36
F36: Tiền tồn cuối kỳ | G36: =G35+G34 | H36: =H34+H35 | I36: =I34+I35 | J36: =J34+J35 | K36: =K34+K35 | L36: =L34+L35
